odoo/addons/survey_multi_company/README.rst
odoo/addons/survey_multi_company/__init__.py
odoo/addons/survey_multi_company/__manifest__.py
odoo/addons/survey_multi_company/controllers/__init__.py
odoo/addons/survey_multi_company/controllers/main.py
odoo/addons/survey_multi_company/i18n/it.po
odoo/addons/survey_multi_company/i18n/survey_multi_company.pot
odoo/addons/survey_multi_company/models/__init__.py
odoo/addons/survey_multi_company/models/survey_survey.py
odoo/addons/survey_multi_company/readme/CONTRIBUTORS.md
odoo/addons/survey_multi_company/readme/DESCRIPTION.md
odoo/addons/survey_multi_company/readme/USAGE.md
odoo/addons/survey_multi_company/security/survey_security.xml
odoo/addons/survey_multi_company/static/description/icon.png
odoo/addons/survey_multi_company/static/description/index.html
odoo/addons/survey_multi_company/views/survey_views.xml
odoo_addon_survey_multi_company-17.0.1.0.1.dist-info/METADATA
odoo_addon_survey_multi_company-17.0.1.0.1.dist-info/WHEEL
odoo_addon_survey_multi_company-17.0.1.0.1.dist-info/top_level.txt
odoo_addon_survey_multi_company-17.0.1.0.1.dist-info/RECORD
